zdatalake/__init__.py
zdatalake/cli.py
zdatalake/zdatalake.py
zdatalake-0.1.1.dist-info/LICENSE.txt
zdatalake-0.1.1.dist-info/METADATA
zdatalake-0.1.1.dist-info/RECORD
zdatalake-0.1.1.dist-info/WHEEL
zdatalake-0.1.1.dist-info/entry_points.txt
zdatalake-0.1.1.dist-info/top_level.txt
