Metadata-Version: 2.1
Name: zdatalake
Version: 0.1.1
Summary: Zalando Data Lake client library helpers and CLI
Home-page: https://github.com/zdatalake/zdatalake
Author: Zalando SE
Author-email: elgalu3@gmail.com
License: MIT license
Keywords: zdatalake
Platform: UNKNOWN
Classifier: Development Status :: 2 - Pre-Alpha
Classifier: Intended Audience :: Developers
Classifier: License :: OSI Approved :: MIT License
Classifier: Natural Language :: English
Classifier: Programming Language :: Python :: 2
Classifier: Programming Language :: Python :: 2.7
Classifier: Programming Language :: Python :: 3
Classifier: Programming Language :: Python :: 3.5
Classifier: Programming Language :: Python :: 3.6
Requires-Dist: Click (>=6.0)
